setup.py
vk2tg/__init__.py
vk2tg.egg-info/PKG-INFO
vk2tg.egg-info/SOURCES.txt
vk2tg.egg-info/dependency_links.txt
vk2tg.egg-info/requires.txt
vk2tg.egg-info/top_level.txt