Metadata-Version: 1.1
Name: vk2tg
Version: 0.1.1
Summary: Integration vk with Telegram
Home-page: https://github.com/uburuntu/vk2tg
Author: uburuntu
Author-email: bekbulatov.ramzan@ya.ru
License: GNU General Public License v3.0, see LICENSE file
Download-URL: https://github.com/uburuntu/vk2tg/archive/master.zip
Platform: UNKNOWN
Classifier: Development Status :: 3 - Alpha
Classifier: License :: OSI Approved :: GNU General Public License v3 (GPLv3)
Classifier: Programming Language :: Python :: 3
